iwisdm/__init__.py
iwisdm/core.py
iwisdm/envs/__init__.py
iwisdm/envs/make.py
iwisdm/envs/registration.py
iwisdm/envs/shapenet/__init__.py
iwisdm/envs/shapenet/auto_task_gen.py
iwisdm/envs/shapenet/info_generator.py
iwisdm/envs/shapenet/registration.py
iwisdm/envs/shapenet/shapenet_env.py
iwisdm/envs/shapenet/stim_generator.py
iwisdm/envs/shapenet/task_bank.py
iwisdm/envs/shapenet/task_generator.py
iwisdm/utils/__init__.py
iwisdm/utils/auto_task_gen.py
iwisdm/utils/read_write.py
iwisdm-0.1.3.dist-info/LICENSE
iwisdm-0.1.3.dist-info/METADATA
iwisdm-0.1.3.dist-info/WHEEL
iwisdm-0.1.3.dist-info/RECORD
