Metadata-Version: 2.1
Name: iwisdm
Version: 0.1.3
Summary: A virtual environment that generates vision-language tasks with varying complexity.
License: MIT
Author: Xiaoxuan Lei
Author-email: xiaoxuan.lei@mail.mcgill.ca
Requires-Python: >=3.11,<4.0
Classifier: License :: OSI Approved :: MIT License
Classifier: Programming Language :: Python :: 3
Classifier: Programming Language :: Python :: 3.11
Classifier: Programming Language :: Python :: 3.12
Classifier: Programming Language :: Python :: 3.13
Requires-Dist: matplotlib (>=3.8.3,<4.0.0)
Requires-Dist: natsort (>=8.4.0,<9.0.0)
Requires-Dist: networkx (>=3.2.1,<4.0.0)
Requires-Dist: numpy (>=1.26.4,<2.0.0)
Requires-Dist: opencv-python (>=4.9.0.80,<5.0.0.0)
Requires-Dist: pandas (>=2.2.1,<3.0.0)
